tvoverlay/__init__.py
tvoverlay/const.py
tvoverlay/exceptions.py
tvoverlay/imagehelper.py
tvoverlay/py.typed
tvoverlay/tvoverlay.py
tvoverlay-2.0.2.dist-info/LICENSE
tvoverlay-2.0.2.dist-info/METADATA
tvoverlay-2.0.2.dist-info/WHEEL
tvoverlay-2.0.2.dist-info/RECORD
