Metadata-Version: 2.1
Name: tvoverlay
Version: 2.0.2
Summary: Python API for sending notifications to TvOverlay for Android TV
Home-page: https://github.com/hareeshmu/pytvoverlay
License: MIT
Keywords: tvoverlay,api,async,client
Author: Hareesh M U
Author-email: hareesh.mu@gmail.com
Maintainer: Hareesh M U
Maintainer-email: hareesh.mu@gmail.com
Requires-Python: >=3.11,<4.0
Classifier: Development Status :: 4 - Beta
Classifier: Environment :: Console
Classifier: Framework :: AsyncIO
Classifier: Intended Audience :: Developers
Classifier: License :: OSI Approved :: MIT License
Classifier: Natural Language :: English
Classifier: Operating System :: MacOS :: MacOS X
Classifier: Operating System :: Microsoft :: Windows
Classifier: Operating System :: POSIX
Classifier: Programming Language :: Python :: 3
Classifier: Programming Language :: Python :: 3.11
Classifier: Programming Language :: Python :: 3.12
Classifier: Topic :: Software Development :: Libraries :: Python Modules
Requires-Dist: aiofiles (>=23.2.1,<24.0.0)
Requires-Dist: aiohttp (>=3.0.0)
Requires-Dist: awesomeversion (>=22.1.0)
Requires-Dist: backoff (>=2.2.0)
Requires-Dist: cachetools (>=4.0.0)
Requires-Dist: httpx (>=0.23,<1)
Requires-Dist: yarl (>=1.6.0)
Project-URL: Bug Tracker, https://github.com/hareeshmu/pytvoverlay/issues
Project-URL: Changelog, https://github.com/hareeshmu/pytvoverlay/releases
Project-URL: Documentation, https://github.com/hareeshmu/pytvoverlay
Project-URL: Repository, https://github.com/hareeshmu/pytvoverlay/releases
